jrnlsh/__init__.py
jrnlsh-0.0.7.dist-info/LICENSE
jrnlsh-0.0.7.dist-info/METADATA
jrnlsh-0.0.7.dist-info/WHEEL
jrnlsh-0.0.7.dist-info/entry_points.txt
jrnlsh-0.0.7.dist-info/top_level.txt
jrnlsh-0.0.7.dist-info/RECORD
