Metadata-Version: 2.1
Name: jrnlsh
Version: 0.0.7
Summary: A simple shell wrapper for jrnl and timewarrior
Home-page: http://github.com/darkpixel/jrnlsh
Author: Aaron C. de Bruyn
Author-email: aaron@heyaaron.com
License: MIT
License-File: LICENSE
